jet/__init__.py
jet/admin.py
jet/apps.py
jet/dashboard/__init__.py
jet/dashboard/apps.py
jet/dashboard/checks.py
jet/dashboard/dashboard.py
jet/dashboard/forms.py
jet/dashboard/locale/ar/LC_MESSAGES/django.mo
jet/dashboard/locale/ar/LC_MESSAGES/django.po
jet/dashboard/locale/ar/LC_MESSAGES/djangojs.mo
jet/dashboard/locale/ar/LC_MESSAGES/djangojs.po
jet/dashboard/locale/cs/LC_MESSAGES/django.mo
jet/dashboard/locale/cs/LC_MESSAGES/django.po
jet/dashboard/locale/cs/LC_MESSAGES/djangojs.mo
jet/dashboard/locale/cs/LC_MESSAGES/djangojs.po
jet/dashboard/locale/de/LC_MESSAGES/django.mo
jet/dashboard/locale/de/LC_MESSAGES/django.po
jet/dashboard/locale/de/LC_MESSAGES/djangojs.mo
jet/dashboard/locale/de/LC_MESSAGES/djangojs.po
jet/dashboard/locale/en/LC_MESSAGES/django.mo
jet/dashboard/locale/en/LC_MESSAGES/django.po
jet/dashboard/locale/en/LC_MESSAGES/djangojs.mo
jet/dashboard/locale/en/LC_MESSAGES/djangojs.po
jet/dashboard/locale/es/LC_MESSAGES/django.mo
jet/dashboard/locale/es/LC_MESSAGES/django.po
jet/dashboard/locale/es/LC_MESSAGES/djangojs.mo
jet/dashboard/locale/es/LC_MESSAGES/djangojs.po
jet/dashboard/locale/fa/LC_MESSAGES/django.mo
jet/dashboard/locale/fa/LC_MESSAGES/django.po
jet/dashboard/locale/fa/LC_MESSAGES/djangojs.mo
jet/dashboard/locale/fa/LC_MESSAGES/djangojs.po
jet/dashboard/locale/fr/LC_MESSAGES/django.mo
jet/dashboard/locale/fr/LC_MESSAGES/django.po
jet/dashboard/locale/fr/LC_MESSAGES/djangojs.mo
jet/dashboard/locale/fr/LC_MESSAGES/djangojs.po
jet/dashboard/locale/pl/LC_MESSAGES/django.mo
jet/dashboard/locale/pl/LC_MESSAGES/django.po
jet/dashboard/locale/pt-br/LC_MESSAGES/django.mo
jet/dashboard/locale/pt-br/LC_MESSAGES/django.po
jet/dashboard/locale/pt-br/LC_MESSAGES/djangojs.mo
jet/dashboard/locale/pt-br/LC_MESSAGES/djangojs.po
jet/dashboard/locale/ru/LC_MESSAGES/django.mo
jet/dashboard/locale/ru/LC_MESSAGES/django.po
jet/dashboard/locale/ru/LC_MESSAGES/djangojs.mo
jet/dashboard/locale/ru/LC_MESSAGES/djangojs.po
djet2-1.0.9a4.dist-info/LICENSE
djet2-1.0.9a4.dist-info/WHEEL
djet2-1.0.9a4.dist-info/METADATA
djet2-1.0.9a4.dist-info/RECORD
