Metadata-Version: 2.1
Name: djet2
Version: 1.0.9a4
Summary: Modern template for Django admin interface with improved functionality
Home-page: https://github.com/vanyakosmos/djet2
License: AGPL-3.0
Keywords: django,admin,ui
Author: Denis Kildishev
Author-email: support@jet.geex-arts.com
Maintainer: Bachynin Ivan
Maintainer-email: bachynin.i@gmail.com
Requires-Python: >=3.7,<4.0
Classifier: Development Status :: 3 - Alpha
Classifier: Environment :: Web Environment
Classifier: Framework :: Django
Classifier: Intended Audience :: Developers
Classifier: Intended Audience :: System Administrators
Classifier: License :: OSI Approved :: GNU Affero General Public License v3
Classifier: Operating System :: OS Independent
Classifier: Programming Language :: Python
Classifier: Programming Language :: Python :: 3
Classifier: Programming Language :: Python :: 3.7
Classifier: Programming Language :: Python :: 3.8
Classifier: Topic :: Software Development
Classifier: Topic :: Software Development :: User Interfaces
Provides-Extra: google_analytics
Requires-Dist: django (>=3,<4)
Requires-Dist: django-autocomplete-light (>=3.5.1,<4.0.0)
Requires-Dist: google-api-python-client (==1.4.1); extra == "google_analytics"
